tciaclient/__init__.py
tciaclient/_nbdev.py
tciaclient/core.py
tciaclient-0.0.3.dist-info/LICENSE
tciaclient-0.0.3.dist-info/METADATA
tciaclient-0.0.3.dist-info/WHEEL
tciaclient-0.0.3.dist-info/entry_points.txt
tciaclient-0.0.3.dist-info/top_level.txt
tciaclient-0.0.3.dist-info/RECORD
