Metadata-Version: 2.1
Name: tciaclient
Version: 0.0.3
Summary: TCIA (The Cancer Imaging Archive) Download Client for Python
Home-page: https://github.com/moritzschwyzer/tciaclient/tree/master/
Author: Moritz Schwyzer
Author-email: moritz.schwyzer@usz.ch
License: Apache Software License 2.0
Keywords: TCIA,medical imaging,download
Platform: UNKNOWN
Classifier: Development Status :: 3 - Alpha
Classifier: Intended Audience :: Developers
Classifier: Natural Language :: English
Classifier: Programming Language :: Python :: 3.6
Classifier: Programming Language :: Python :: 3.7
Classifier: Programming Language :: Python :: 3.8
Classifier: License :: OSI Approved :: Apache Software License
Requires-Python: >=3.6
Requires-Dist: pip
Requires-Dist: packaging
Provides-Extra: dev
